setup.py
cherry_distribution/Binomialdistribution.py
cherry_distribution/Gaussiandistribution.py
cherry_distribution/Generaldistribution.py
cherry_distribution/__init__.py
cherry_distribution.egg-info/PKG-INFO
cherry_distribution.egg-info/SOURCES.txt
cherry_distribution.egg-info/dependency_links.txt
cherry_distribution.egg-info/not-zip-safe
cherry_distribution.egg-info/top_level.txt