Metadata-Version: 1.0
Name: cherry-distribution
Version: 0.1
Summary: Hello Fuss
Home-page: UNKNOWN
Author: UNKNOWN
Author-email: UNKNOWN
License: UNKNOWN
Platform: UNKNOWN
